[
    {
        "id": 1747371946,
        "your-name": "bim",
        "your-number": "09383419000",
        "your-email": "vinakrstn01@gmail.com",
        "message": "galing",
        "rating": "5",
        "Approved": "Pending",
        "timestamp": "2025-05-16 05:05:46"
    },
    {
        "id": 1747386053,
        "your-name": "Leng Alejandro",
        "your-number": "09172486214",
        "your-email": "rosaliealejandro@gmail.com",
        "message": "thank you!\r\n:)",
        "rating": "5",
        "Approved": "Approved",
        "timestamp": "2025-05-16 09:00:53"
    },
    {
        "id": 1747386453,
        "your-name": "Grace eme",
        "your-number": "09088982556",
        "your-email": "rosaliealejandro@gmail.com",
        "message": "Hooorrraaayyyy!!!",
        "rating": "5",
        "Approved": "Pending",
        "timestamp": "2025-05-16 09:07:33"
    },
    {
        "id": 1747656304,
        "your-name": "Emmanuel Cabriana",
        "your-number": "09915665243",
        "your-email": "emmanueljazcabriana321@gmail.com",
        "message": "I love UYU CHA!",
        "rating": "5",
        "Approved": "Approved",
        "timestamp": "2025-05-19 12:05:04"
    },
    {
        "id": 1747656411,
        "your-name": "Emmanuel Cabriana",
        "your-number": "09915665243",
        "your-email": "emmanueljazcabriana321@gmail.com",
        "message": "I love UYU CHA!",
        "rating": "5",
        "Approved": "Pending",
        "timestamp": "2025-05-19 12:06:51"
    },
    {
        "id": 1747656559,
        "your-name": "Emmanuel Cabriana",
        "your-number": "09915665243",
        "your-email": "emmanueljazcabriana321@gmail.com",
        "message": "I love UYU CHA!",
        "rating": "5",
        "Approved": "Pending",
        "timestamp": "2025-05-19 12:09:19"
    },
    {
        "id": 1754481366,
        "your-name": "Daniel Sanchez",
        "your-number": "09632173515",
        "your-email": "dsdanielsanchez123@gmail.com",
        "message": "Great",
        "rating": "5",
        "Approved": "Approved",
        "timestamp": "2025-08-06 11:56:06"
    },
    {
        "id": 1754481662,
        "your-name": "Ali Cabriana",
        "your-number": "09943703377",
        "your-email": "alizacabriana041006@gmail.com",
        "message": "The best! Very affordable and super sarap!!\ud83e\ude77",
        "rating": "5",
        "Approved": "Pending",
        "timestamp": "2025-08-06 12:01:02"
    }
]